difficult_dialogs
