Metadata-Version: 1.0
Name: difficult-dialogs
Version: 0.3
Summary: Tools to easily guide conversations towards a certain objective
Home-page: https://github.com/JarbasAl/difficult_dialogs
Author: jarbasAI
Author-email: jarbasai@mailfence.com
License: MIT
Platform: UNKNOWN
